categories/__init__.py
categories/_builtins.py
categories/applicative.py
categories/bifunctor.py
categories/builtins.py
categories/either.py
categories/functor.py
categories/instances.py
categories/maybe.py
categories/monad.py
categories/monoid.py
categories/semigroup.py
categories/utils.py
categories/validation.py
pycategories-1.2.0.dist-info/METADATA
pycategories-1.2.0.dist-info/RECORD
pycategories-1.2.0.dist-info/WHEEL
pycategories-1.2.0.dist-info/top_level.txt
