Metadata-Version: 2.1
Name: pycategories
Version: 1.2.0
Summary: Implementation of some concepts from category theory
Home-page: https://gitlab.com/danielhones/pycategories
Author: Daniel Hones
License: MIT
Keywords: category theory,monoid,functor,applicative,monad,haskell
Platform: UNKNOWN
Classifier: Programming Language :: Python :: 3.4
Classifier: Programming Language :: Python :: 3.5
Classifier: Programming Language :: Python :: 3.6
Provides-Extra: docs
Provides-Extra: dev
Requires-Dist: infix (==1.2)
Provides-Extra: dev
Requires-Dist: flake8 (==3.6.0); extra == 'dev'
Requires-Dist: flake8-per-file-ignores (==0.6); extra == 'dev'
Requires-Dist: mypy (==0.670); extra == 'dev'
Requires-Dist: pytest; extra == 'dev'
Requires-Dist: pytest-cov; extra == 'dev'
Provides-Extra: docs
Requires-Dist: Sphinx; extra == 'docs'
Requires-Dist: sphinx-rtd-theme; extra == 'docs'
Requires-Dist: flake8 (==3.6.0); extra == 'docs'
Requires-Dist: flake8-per-file-ignores (==0.6); extra == 'docs'
Requires-Dist: mypy (==0.670); extra == 'docs'
Requires-Dist: pytest; extra == 'docs'
Requires-Dist: pytest-cov; extra == 'docs'
